MyGaiaDB-0.5.1.dist-info/RECORD
MyGaiaDB-0.5.1.dist-info/WHEEL
MyGaiaDB-0.5.1.dist-info/LICENSE
MyGaiaDB-0.5.1.dist-info/top_level.txt
MyGaiaDB-0.5.1.dist-info/METADATA
mygaiadb/astroqlite_c.cpython-312-x86_64-linux-gnu.so
mygaiadb/utils.py
mygaiadb/__init__.py
mygaiadb/query/__init__.py
mygaiadb/query/query.py
mygaiadb/query/callbacks.py
mygaiadb/spec/__init__.py
mygaiadb/data/__init__.py
mygaiadb/data/download.py
mygaiadb/data/compile.py
mygaiadb/data/sql_schema/gaia_source_schema.sql
mygaiadb/data/sql_schema/allwise_lite_schema.sql
mygaiadb/data/sql_schema/astrophysical_parameters_schema.sql
mygaiadb/data/sql_schema/tmasspscxsc_best_neighbour_schema.sql
mygaiadb/data/sql_schema/twomass_psc_lite_schema.sql
mygaiadb/data/sql_schema/allwise_best_neighbour_schema.sql
mygaiadb/data/sql_schema/astrophysical_parameters_lite_schema.sql
mygaiadb/data/sql_schema/catwise_lite_schema.sql
mygaiadb/data/sql_schema/gaia_source_lite_schema.sql
mygaiadb/ext_c/astroqlite.c
