Metadata-Version: 2.1
Name: MyGaiaDB
Version: 0.5.1
Summary: Setup local serverless SQL Gaia/2MASS/ALLWISE/CATWISE databases and run query locally with python
Author-email: Henry Leung <henryskyleung@gmail.com>
Maintainer-email: Henry Leung <henryskyleung@gmail.com>
License: Copyright 2023-2024 Henry Leung
Project-URL: Homepage, https://github.com/henrysky/MyGaiaDB
Project-URL: Documentation, https://github.com/henrysky/MyGaiaDB
Project-URL: Repository, https://github.com/henrysky/MyGaiaDB
Project-URL: Bug Tracker, https://github.com/henrysky/MyGaiaDB/issues
Classifier: Development Status :: 4 - Beta
Classifier: License :: OSI Approved :: MIT License
Classifier: Programming Language :: Python
Classifier: Intended Audience :: Science/Research
Classifier: Topic :: Scientific/Engineering :: Astronomy
Classifier: Topic :: Database :: Database Engines/Servers
Classifier: Topic :: Database :: Front-Ends
Requires-Python: >=3.8
License-File: LICENSE
Requires-Dist: numpy
Requires-Dist: astropy
Requires-Dist: h5py
Requires-Dist: pandas
Requires-Dist: tqdm
Requires-Dist: wheel
Requires-Dist: requests
